{"Bloom":{"Bloom":{"internalLink":{"count":2,"lastUpdated":1699779211007}}},"Astra":{"Astra":{"internalLink":{"count":1,"lastUpdated":1699780437591}}},"Fontaine":{"Fontaine":{"currentFile":{"count":2,"lastUpdated":1699859739308},"internalLink":{"count":1,"lastUpdated":1699859742696}}},"Reverie":{"Reverie":{"internalLink":{"count":6,"lastUpdated":1699861907784}}},"Miroirs":{"Miroirs":{"internalLink":{"count":5,"lastUpdated":1699861911042}}},"UnderMont":{"UnderMont":{"internalLink":{"count":4,"lastUpdated":1699861913482}}},"Parhelion":{"Parhelion":{"internalLink":{"count":4,"lastUpdated":1699859736414}}},"Sol":{"Sol":{"internalLink":{"count":1,"lastUpdated":1699781186324}}},"Aspects":{"Aspects":{"internalLink":{"count":4,"lastUpdated":1699859907079}}},"lawmage-ggr":{"lawmage-ggr":{"internalLink":{"count":1,"lastUpdated":1699783621500}}},"foresight":{"foresight":{"internalLink":{"count":1,"lastUpdated":1699783645000}}},"Astrale":{"Astrale":{"internalLink":{"count":4,"lastUpdated":1699861894959}}},"owlin-scc":{"owlin-scc":{"internalLink":{"count":3,"lastUpdated":1699862081103}}},"Potential":{"Potential":{"currentFile":{"count":1,"lastUpdated":1699783980733}}},"dragonborn":{"dragonborn":{"internalLink":{"count":2,"lastUpdated":1699861960533}}},"dwarf":{"dwarf":{"internalLink":{"count":2,"lastUpdated":1699861731476}}},"elf":{"elf":{"internalLink":{"count":2,"lastUpdated":1699861555363}}},"gnome":{"gnome":{"internalLink":{"count":2,"lastUpdated":1699861736781}}},"half-elf":{"half-elf":{"internalLink":{"count":2,"lastUpdated":1699861776024}}},"halfling":{"halfling":{"internalLink":{"count":2,"lastUpdated":1699861792959}}},"half-orc":{"half-orc":{"internalLink":{"count":2,"lastUpdated":1699861972227}}},"human":{"human":{"internalLink":{"count":2,"lastUpdated":1699861709169}}},"tiefling":{"tiefling":{"internalLink":{"count":3,"lastUpdated":1699861492162}}},"aarakocra":{"aarakocra":{"internalLink":{"count":2,"lastUpdated":1699861967823}}},"aasimar-dmg":{"aasimar-dmg":{"internalLink":{"count":2,"lastUpdated":1699861486632}}},"genasi-mpmm":{"genasi-mpmm":{"internalLink":{"count":1,"lastUpdated":1699860180740}}},"bugbear":{"bugbear":{"internalLink":{"count":2,"lastUpdated":1699861957380}}},"centaur":{"centaur":{"internalLink":{"count":2,"lastUpdated":1699861715036}}},"changeling-mpmm":{"changeling-mpmm":{"internalLink":{"count":2,"lastUpdated":1699861537484}}},"deep-gnome-mpmm":{"deep-gnome-mpmm":{"internalLink":{"count":2,"lastUpdated":1699861718299}}},"duergar-mpmm":{"duergar-mpmm":{"internalLink":{"count":2,"lastUpdated":1699861747407}}},"eladrin-mpmm":{"eladrin-mpmm":{"internalLink":{"count":2,"lastUpdated":1699861525589}}},"fairy-mpmm":{"fairy-mpmm":{"internalLink":{"count":3,"lastUpdated":1699861983708}}},"firbolg-mpmm":{"firbolg-mpmm":{"internalLink":{"count":2,"lastUpdated":1699861977216}}},"githzerai-mpmm":{"githzerai-mpmm":{"internalLink":{"count":2,"lastUpdated":1699862129066}}},"githyanki-mpmm":{"githyanki-mpmm":{"internalLink":{"count":2,"lastUpdated":1699862132507}}},"goblin":{"goblin":{"internalLink":{"count":2,"lastUpdated":1699861990403}}},"goliath-mpmm":{"goliath-mpmm":{"internalLink":{"count":2,"lastUpdated":1699861998217}}},"harengon-mpmm":{"harengon-mpmm":{"internalLink":{"count":2,"lastUpdated":1699862007351}}},"hobgoblin-dmg":{"hobgoblin-dmg":{"internalLink":{"count":1,"lastUpdated":1699860288635}}},"kenku":{"kenku":{"internalLink":{"count":3,"lastUpdated":1699861627282}}},"kobold":{"kobold":{"internalLink":{"count":2,"lastUpdated":1699862012155}}},"lizardfolk":{"lizardfolk":{"internalLink":{"count":3,"lastUpdated":1699936819127}}},"minotaur-mpmm":{"minotaur-mpmm":{"internalLink":{"count":2,"lastUpdated":1699862026416}}},"orc-mpmm":{"orc-mpmm":{"internalLink":{"count":2,"lastUpdated":1699862029773}}},"satyr-mpmm":{"satyr-mpmm":{"internalLink":{"count":2,"lastUpdated":1699862036960}}},"shadar-kai-mpmm":{"shadar-kai-mpmm":{"internalLink":{"count":2,"lastUpdated":1699861546381}}},"shifter-mpmm":{"shifter-mpmm":{"internalLink":{"count":2,"lastUpdated":1699861725496}}},"tabaxi-mpmm":{"tabaxi-mpmm":{"internalLink":{"count":2,"lastUpdated":1699862044093}}},"tortle-mpmm":{"tortle-mpmm":{"internalLink":{"count":2,"lastUpdated":1699862048661}}},"triton-mpmm":{"triton-mpmm":{"internalLink":{"count":2,"lastUpdated":1699861759256}}},"yuan-ti-mpmm":{"yuan-ti-mpmm":{"internalLink":{"count":2,"lastUpdated":1699862052366}}},"giff-mpmm":{"giff-mpmm":{"internalLink":{"count":2,"lastUpdated":1699862140078}}},"kalashtar-erlw":{"kalashtar-erlw":{"internalLink":{"count":2,"lastUpdated":1699861650222}}},"leonin-mot":{"leonin-mot":{"internalLink":{"count":2,"lastUpdated":1699862087860}}},"warforged-erlw":{"warforged-erlw":{"internalLink":{"count":2,"lastUpdated":1699862135929}}},"loxodon-ggr":{"loxodon-ggr":{"internalLink":{"count":2,"lastUpdated":1699862090508}}},"Void":{"Void":{"internalLink":{"count":3,"lastUpdated":1699861915809}}},"races":{"races":{"internalLink":{"count":1,"lastUpdated":1699862123626}}},"Colhen":{"Colhen":{"internalLink":{"count":1,"lastUpdated":1699929050037}}},"Rocheste":{"Rocheste":{"internalLink":{"count":4,"lastUpdated":1699936385078}}},"Ainle":{"Ainle":{"internalLink":{"count":2,"lastUpdated":1699933973451}}},"gnoll":{"gnoll":{"internalLink":{"count":2,"lastUpdated":1699933953664}}},"bard":{"bard":{"internalLink":{"count":2,"lastUpdated":1699936435828}}},"Castle":{"Castle":{"currentFile":{"count":1,"lastUpdated":1699936236565}}},"Island":{"Island":{"currentFile":{"count":1,"lastUpdated":1699936680013}}}}